LICENSE.tmplt
LICENSE.txt
MANIFEST.in
Makefile
Makefile.inc
PackageInfo.cfg
README.txt
info.py
pygmyplot.pdf
setup.py
docsrc/Makefile
docsrc/conf.py
docsrc/heat_2d.png
docsrc/index.rst
docsrc/scatter-hist.png
docsrc/xy_heat.png
docsrc/xy_plot.png
docsrc/_build/html/_images/heat_2d.png
docsrc/_build/html/_images/scatter-hist.png
docsrc/_build/html/_images/xy_heat.png
docsrc/_build/html/_images/xy_plot.png
docsrc/_build/html/_static/comment-bright.png
docsrc/_build/html/_static/comment-close.png
docsrc/_build/html/_static/comment.png
docsrc/_build/html/_static/down-pressed.png
docsrc/_build/html/_static/down.png
docsrc/_build/html/_static/file.png
docsrc/_build/html/_static/minus.png
docsrc/_build/html/_static/plus.png
docsrc/_build/html/_static/up-pressed.png
docsrc/_build/html/_static/up.png
docsrc/_build/latex/heat_2d.png
docsrc/_build/latex/scatter-hist.png
docsrc/_build/latex/xy_heat.png
docsrc/_build/latex/xy_plot.png
html/genindex.html
html/index.html
html/objects.inv
html/search.html
html/searchindex.js
html/_images/heat_2d.png
html/_images/scatter-hist.png
html/_images/xy_heat.png
html/_images/xy_plot.png
html/_modules/index.html
html/_modules/pygmyplot.html
html/_sources/index.txt
html/_static/ajax-loader.gif
html/_static/basic.css
html/_static/comment-bright.png
html/_static/comment-close.png
html/_static/comment.png
html/_static/default.css
html/_static/doctools.js
html/_static/down-pressed.png
html/_static/down.png
html/_static/file.png
html/_static/jquery.js
html/_static/minus.png
html/_static/plus.png
html/_static/pygments.css
html/_static/searchtools.js
html/_static/sidebar.js
html/_static/underscore.js
html/_static/up-pressed.png
html/_static/up.png
html/_static/websupport.js
pygmyplot/__init__.py
pygmyplot/_version.py
pygmyplot/pygmyplotlib.py
pygmyplot.egg-info/PKG-INFO
pygmyplot.egg-info/SOURCES.txt
pygmyplot.egg-info/dependency_links.txt
pygmyplot.egg-info/requires.txt
pygmyplot.egg-info/top_level.txt