Metadata-Version: 1.0
Name: pygmyplot
Version: 0.2.10rc
Summary: Matplotlib wrapper plotting library
Home-page: http://pygmyplot.bravais.net
Author: James C. Stroud
Author-email: jstroud@mbi.ucla.edu
License: LICENSE.txt
Platform: UNKNOWN
Classifier: Development Status :: 4 - Beta
Classifier: Environment :: MacOS X :: Aqua
Classifier: Intended Audience :: Developers
Classifier: Intended Audience :: Science/Research
Classifier: License :: OSI Approved :: GNU General Public License (GPL)
Classifier: Natural Language :: English
Classifier: Programming Language :: Python :: 2.6
Classifier: Programming Language :: Python :: 2.7
Classifier: Topic :: Scientific/Engineering :: Visualization
